binance_websocket/__init__.py
binance_websocket/websocket.py
binance_websocket-0.0.1.dist-info/LICENSE
binance_websocket-0.0.1.dist-info/METADATA
binance_websocket-0.0.1.dist-info/WHEEL
binance_websocket-0.0.1.dist-info/top_level.txt
binance_websocket-0.0.1.dist-info/RECORD
